crudeoil/__init__.py
crudeoil/crudeoil.py
crudeoil/static_vals.py
crudeoil-0.1.0.dist-info/LICENSE
crudeoil-0.1.0.dist-info/METADATA
crudeoil-0.1.0.dist-info/WHEEL
crudeoil-0.1.0.dist-info/top_level.txt
crudeoil-0.1.0.dist-info/RECORD
